{"nodes": [{"id": "users_kika_hub_kika_main_akakika_akakika_src_undrdrgraph_tsx", "label": "UndrdrGraph.tsx", "file_type": "code", "source_file": "/Users/kika_hub/_KIKA_MAIN/AKAKIKA@/akakika/src/UndrdrGraph.tsx", "source_location": "L1"}, {"id": "undrdrgraph_getgroup", "label": "getGroup()", "file_type": "code", "source_file": "/Users/kika_hub/_KIKA_MAIN/AKAKIKA@/akakika/src/UndrdrGraph.tsx", "source_location": "L57"}, {"id": "undrdrgraph_tick", "label": "tick()", "file_type": "code", "source_file": "/Users/kika_hub/_KIKA_MAIN/AKAKIKA@/akakika/src/UndrdrGraph.tsx", "source_location": "L217"}, {"id": "undrdrgraph_findnode", "label": "findNode()", "file_type": "code", "source_file": "/Users/kika_hub/_KIKA_MAIN/AKAKIKA@/akakika/src/UndrdrGraph.tsx", "source_location": "L248"}, {"id": "undrdrgraph_handlemousemove", "label": "handleMouseMove()", "file_type": "code", "source_file": "/Users/kika_hub/_KIKA_MAIN/AKAKIKA@/akakika/src/UndrdrGraph.tsx", "source_location": "L260"}, {"id": "undrdrgraph_handlemousedown", "label": "handleMouseDown()", "file_type": "code", "source_file": "/Users/kika_hub/_KIKA_MAIN/AKAKIKA@/akakika/src/UndrdrGraph.tsx", "source_location": "L283"}, {"id": "undrdrgraph_handlemouseup", "label": "handleMouseUp()", "file_type": "code", "source_file": "/Users/kika_hub/_KIKA_MAIN/AKAKIKA@/akakika/src/UndrdrGraph.tsx", "source_location": "L299"}, {"id": "undrdrgraph_handlewheel", "label": "handleWheel()", "file_type": "code", "source_file": "/Users/kika_hub/_KIKA_MAIN/AKAKIKA@/akakika/src/UndrdrGraph.tsx", "source_location": "L301"}, {"id": "undrdrgraph_handleclick", "label": "handleClick()", "file_type": "code", "source_file": "/Users/kika_hub/_KIKA_MAIN/AKAKIKA@/akakika/src/UndrdrGraph.tsx", "source_location": "L307"}, {"id": "undrdrgraph_zoomin", "label": "zoomIn()", "file_type": "code", "source_file": "/Users/kika_hub/_KIKA_MAIN/AKAKIKA@/akakika/src/UndrdrGraph.tsx", "source_location": "L364"}, {"id": "undrdrgraph_zoomout", "label": "zoomOut()", "file_type": "code", "source_file": "/Users/kika_hub/_KIKA_MAIN/AKAKIKA@/akakika/src/UndrdrGraph.tsx", "source_location": "L365"}, {"id": "undrdrgraph_zoomreset", "label": "zoomReset()", "file_type": "code", "source_file": "/Users/kika_hub/_KIKA_MAIN/AKAKIKA@/akakika/src/UndrdrGraph.tsx", "source_location": "L366"}], "edges": [{"source": "users_kika_hub_kika_main_akakika_akakika_src_undrdrgraph_tsx", "target": "react", "relation": "imports_from", "confidence": "EXTRACTED", "source_file": "/Users/kika_hub/_KIKA_MAIN/AKAKIKA@/akakika/src/UndrdrGraph.tsx", "source_location": "L1", "weight": 1.0}, {"source": "users_kika_hub_kika_main_akakika_akakika_src_undrdrgraph_tsx", "target": "react", "relation": "imports_from", "confidence": "EXTRACTED", "source_file": "/Users/kika_hub/_KIKA_MAIN/AKAKIKA@/akakika/src/UndrdrGraph.tsx", "source_location": "L2", "weight": 1.0}, {"source": "users_kika_hub_kika_main_akakika_akakika_src_undrdrgraph_tsx", "target": "undrdrgraph_getgroup", "relation": "contains", "confidence": "EXTRACTED", "source_file": "/Users/kika_hub/_KIKA_MAIN/AKAKIKA@/akakika/src/UndrdrGraph.tsx", "source_location": "L57", "weight": 1.0}, {"source": "users_kika_hub_kika_main_akakika_akakika_src_undrdrgraph_tsx", "target": "undrdrgraph_tick", "relation": "contains", "confidence": "EXTRACTED", "source_file": "/Users/kika_hub/_KIKA_MAIN/AKAKIKA@/akakika/src/UndrdrGraph.tsx", "source_location": "L217", "weight": 1.0}, {"source": "users_kika_hub_kika_main_akakika_akakika_src_undrdrgraph_tsx", "target": "undrdrgraph_findnode", "relation": "contains", "confidence": "EXTRACTED", "source_file": "/Users/kika_hub/_KIKA_MAIN/AKAKIKA@/akakika/src/UndrdrGraph.tsx", "source_location": "L248", "weight": 1.0}, {"source": "users_kika_hub_kika_main_akakika_akakika_src_undrdrgraph_tsx", "target": "undrdrgraph_handlemousemove", "relation": "contains", "confidence": "EXTRACTED", "source_file": "/Users/kika_hub/_KIKA_MAIN/AKAKIKA@/akakika/src/UndrdrGraph.tsx", "source_location": "L260", "weight": 1.0}, {"source": "users_kika_hub_kika_main_akakika_akakika_src_undrdrgraph_tsx", "target": "undrdrgraph_handlemousedown", "relation": "contains", "confidence": "EXTRACTED", "source_file": "/Users/kika_hub/_KIKA_MAIN/AKAKIKA@/akakika/src/UndrdrGraph.tsx", "source_location": "L283", "weight": 1.0}, {"source": "users_kika_hub_kika_main_akakika_akakika_src_undrdrgraph_tsx", "target": "undrdrgraph_handlemouseup", "relation": "contains", "confidence": "EXTRACTED", "source_file": "/Users/kika_hub/_KIKA_MAIN/AKAKIKA@/akakika/src/UndrdrGraph.tsx", "source_location": "L299", "weight": 1.0}, {"source": "users_kika_hub_kika_main_akakika_akakika_src_undrdrgraph_tsx", "target": "undrdrgraph_handlewheel", "relation": "contains", "confidence": "EXTRACTED", "source_file": "/Users/kika_hub/_KIKA_MAIN/AKAKIKA@/akakika/src/UndrdrGraph.tsx", "source_location": "L301", "weight": 1.0}, {"source": "users_kika_hub_kika_main_akakika_akakika_src_undrdrgraph_tsx", "target": "undrdrgraph_handleclick", "relation": "contains", "confidence": "EXTRACTED", "source_file": "/Users/kika_hub/_KIKA_MAIN/AKAKIKA@/akakika/src/UndrdrGraph.tsx", "source_location": "L307", "weight": 1.0}, {"source": "users_kika_hub_kika_main_akakika_akakika_src_undrdrgraph_tsx", "target": "undrdrgraph_zoomin", "relation": "contains", "confidence": "EXTRACTED", "source_file": "/Users/kika_hub/_KIKA_MAIN/AKAKIKA@/akakika/src/UndrdrGraph.tsx", "source_location": "L364", "weight": 1.0}, {"source": "users_kika_hub_kika_main_akakika_akakika_src_undrdrgraph_tsx", "target": "undrdrgraph_zoomout", "relation": "contains", "confidence": "EXTRACTED", "source_file": "/Users/kika_hub/_KIKA_MAIN/AKAKIKA@/akakika/src/UndrdrGraph.tsx", "source_location": "L365", "weight": 1.0}, {"source": "users_kika_hub_kika_main_akakika_akakika_src_undrdrgraph_tsx", "target": "undrdrgraph_zoomreset", "relation": "contains", "confidence": "EXTRACTED", "source_file": "/Users/kika_hub/_KIKA_MAIN/AKAKIKA@/akakika/src/UndrdrGraph.tsx", "source_location": "L366", "weight": 1.0}, {"source": "undrdrgraph_handlemousemove", "target": "undrdrgraph_findnode", "relation": "calls", "confidence": "EXTRACTED", "source_file": "/Users/kika_hub/_KIKA_MAIN/AKAKIKA@/akakika/src/UndrdrGraph.tsx", "source_location": "L278", "weight": 1.0}, {"source": "undrdrgraph_handlemousedown", "target": "undrdrgraph_findnode", "relation": "calls", "confidence": "EXTRACTED", "source_file": "/Users/kika_hub/_KIKA_MAIN/AKAKIKA@/akakika/src/UndrdrGraph.tsx", "source_location": "L289", "weight": 1.0}, {"source": "undrdrgraph_handleclick", "target": "undrdrgraph_findnode", "relation": "calls", "confidence": "EXTRACTED", "source_file": "/Users/kika_hub/_KIKA_MAIN/AKAKIKA@/akakika/src/UndrdrGraph.tsx", "source_location": "L310", "weight": 1.0}], "raw_calls": [{"caller_nid": "undrdrgraph_getgroup", "callee": "entries", "source_file": "/Users/kika_hub/_KIKA_MAIN/AKAKIKA@/akakika/src/UndrdrGraph.tsx", "source_location": "L58"}, {"caller_nid": "undrdrgraph_getgroup", "callee": "includes", "source_file": "/Users/kika_hub/_KIKA_MAIN/AKAKIKA@/akakika/src/UndrdrGraph.tsx", "source_location": "L59"}, {"caller_nid": "undrdrgraph_tick", "callee": "sin", "source_file": "/Users/kika_hub/_KIKA_MAIN/AKAKIKA@/akakika/src/UndrdrGraph.tsx", "source_location": "L226"}, {"caller_nid": "undrdrgraph_tick", "callee": "cos", "source_file": "/Users/kika_hub/_KIKA_MAIN/AKAKIKA@/akakika/src/UndrdrGraph.tsx", "source_location": "L227"}, {"caller_nid": "undrdrgraph_tick", "callee": "set", "source_file": "/Users/kika_hub/_KIKA_MAIN/AKAKIKA@/akakika/src/UndrdrGraph.tsx", "source_location": "L239"}, {"caller_nid": "undrdrgraph_tick", "callee": "setPositions", "source_file": "/Users/kika_hub/_KIKA_MAIN/AKAKIKA@/akakika/src/UndrdrGraph.tsx", "source_location": "L240"}, {"caller_nid": "undrdrgraph_tick", "callee": "requestAnimationFrame", "source_file": "/Users/kika_hub/_KIKA_MAIN/AKAKIKA@/akakika/src/UndrdrGraph.tsx", "source_location": "L241"}, {"caller_nid": "undrdrgraph_findnode", "callee": "sqrt", "source_file": "/Users/kika_hub/_KIKA_MAIN/AKAKIKA@/akakika/src/UndrdrGraph.tsx", "source_location": "L255"}, {"caller_nid": "undrdrgraph_handlemousemove", "callee": "getBoundingClientRect", "source_file": "/Users/kika_hub/_KIKA_MAIN/AKAKIKA@/akakika/src/UndrdrGraph.tsx", "source_location": "L261"}, {"caller_nid": "undrdrgraph_handlemousemove", "callee": "find", "source_file": "/Users/kika_hub/_KIKA_MAIN/AKAKIKA@/akakika/src/UndrdrGraph.tsx", "source_location": "L266"}, {"caller_nid": "undrdrgraph_handlemousemove", "callee": "setPan", "source_file": "/Users/kika_hub/_KIKA_MAIN/AKAKIKA@/akakika/src/UndrdrGraph.tsx", "source_location": "L274"}, {"caller_nid": "undrdrgraph_handlemousemove", "callee": "setHovered", "source_file": "/Users/kika_hub/_KIKA_MAIN/AKAKIKA@/akakika/src/UndrdrGraph.tsx", "source_location": "L279"}, {"caller_nid": "undrdrgraph_handlemousemove", "callee": "setHoverPos", "source_file": "/Users/kika_hub/_KIKA_MAIN/AKAKIKA@/akakika/src/UndrdrGraph.tsx", "source_location": "L280"}, {"caller_nid": "undrdrgraph_handlemousedown", "callee": "getBoundingClientRect", "source_file": "/Users/kika_hub/_KIKA_MAIN/AKAKIKA@/akakika/src/UndrdrGraph.tsx", "source_location": "L284"}, {"caller_nid": "undrdrgraph_handlewheel", "callee": "preventDefault", "source_file": "/Users/kika_hub/_KIKA_MAIN/AKAKIKA@/akakika/src/UndrdrGraph.tsx", "source_location": "L302"}, {"caller_nid": "undrdrgraph_handlewheel", "callee": "setZoom", "source_file": "/Users/kika_hub/_KIKA_MAIN/AKAKIKA@/akakika/src/UndrdrGraph.tsx", "source_location": "L304"}, {"caller_nid": "undrdrgraph_handleclick", "callee": "getBoundingClientRect", "source_file": "/Users/kika_hub/_KIKA_MAIN/AKAKIKA@/akakika/src/UndrdrGraph.tsx", "source_location": "L308"}, {"caller_nid": "undrdrgraph_handleclick", "callee": "setSelected", "source_file": "/Users/kika_hub/_KIKA_MAIN/AKAKIKA@/akakika/src/UndrdrGraph.tsx", "source_location": "L311"}, {"caller_nid": "undrdrgraph_zoomin", "callee": "setZoom", "source_file": "/Users/kika_hub/_KIKA_MAIN/AKAKIKA@/akakika/src/UndrdrGraph.tsx", "source_location": "L364"}, {"caller_nid": "undrdrgraph_zoomout", "callee": "setZoom", "source_file": "/Users/kika_hub/_KIKA_MAIN/AKAKIKA@/akakika/src/UndrdrGraph.tsx", "source_location": "L365"}, {"caller_nid": "undrdrgraph_zoomreset", "callee": "setZoom", "source_file": "/Users/kika_hub/_KIKA_MAIN/AKAKIKA@/akakika/src/UndrdrGraph.tsx", "source_location": "L366"}, {"caller_nid": "undrdrgraph_zoomreset", "callee": "setPan", "source_file": "/Users/kika_hub/_KIKA_MAIN/AKAKIKA@/akakika/src/UndrdrGraph.tsx", "source_location": "L366"}]}